{
  "tasks": [
    {
      "id": 1,
      "title": "Estudar Programação",
      "description": "Estudar programação pelo curso FSC",
      "time": "morning",
      "status": "done"
    },

    {
      "id": 2,
      "title": "Ler",
      "description": "Ler livro de matemática",
      "time": "morning",
      "status": "done"
    },

    {
      "id": 3,
      "title": "Treinar",
      "description": "Treinar musculação na academia",
      "time": "afternoon",
      "status": "in_progress"
    },

    {
      "id": 4,
      "title": "Fazer compras",
      "description": "ir ao mercado comprar coisas para janta",
      "time": "afternoon",
      "status": "in_progress"
    },

    {
      "id": 5,
      "title": "Descansar",
      "description": "Ver um filme com a família",
      "time": "evening",
      "status": "not_started"
    },
    {
      "id": 6,
      "title": "Meditar",
      "description": "fechar os olhos e meditar",
      "time": "evening",
      "status": "not_started"
    }
  ]
}
